{
    "paintColors": [
        {
            "id": 1,
            "color": "Silver",
            "price": 1300
        },
        {
            "id": 2,
            "color": "Midnight Blue",
            "price": 1350
        },
        {
            "id": 3,
            "color": "Firebrick Red",
            "price": 1500
        },
        {
            "id": 4,
            "color": "Spring Green",
            "price": 1425
        }
    ],
    "interiors": [
        {
            "id": 1,
            "type": "Beige Fabric",
            "price": 800
        },
        {
            "id": 2,
            "type": "Charcoal Fabric",
            "price": 950
        },
        {
            "id": 3,
            "type": "White Leather",
            "price": 1500
        },
        {
            "id": 4,
            "type": "Black Leather",
            "price": 1750
        }
    ],
    "technologies": [
        {
            "id": 1,
            "package": "Basic Package (basic sound system)",
            "price": 300
        },
        {
            "id": 2,
            "package": "Navigation Package (includes integrated navigation controls)",
            "price": 375
        },
        {
            "id": 3,
            "package": "Visibility Package (includes side and reat cameras)",
            "price": 525
        },
        {
            "id": 4,
            "package": "Ultra Package (includes navigation and visibility packages)",
            "price": 600
        }
    ],
    "wheels": [
        {
            "id": 1,
            "wheel": "17-inch Pair Radial",
            "price": 600
        },
        {
            "id": 2,
            "wheel": "17-inch Pair Radial Black",
            "price": 675
        },
        {
            "id": 3,
            "wheel": "18-inch Pair Spoke Silver",
            "price": 800
        },
        {
            "id": 4,
            "wheel": "18-inch Pair Spoke Black",
            "price": 900
        }
    ],
    "orders": [

    ]
}